nissaba/__init__.py
nissaba-0.2.0.dist-info/WHEEL
nissaba-0.2.0.dist-info/METADATA
nissaba-0.2.0.dist-info/RECORD
