Metadata-Version: 2.1
Name: nissaba
Version: 0.2.0
Summary: A utiltiy for managing test results
Home-page: https://github.com/shbroster/nissaba
Author: Samuel Broster
Author-email: s.h.broster+pypi@pm.me
Requires-Python: >=3.6,<4.0
Classifier: Programming Language :: Python :: 3
Classifier: Programming Language :: Python :: 3.6
Classifier: Programming Language :: Python :: 3.7
Classifier: Programming Language :: Python :: 3.8
Project-URL: Repository, https://github.com/shbroster/nissaba
